{"bundler":"rollup","shimport":"1.0.1","assets":{"main":"client.3b61a7af.js"},"css":{"main":["assets/client-431c1c63.css"]},"dependencies":{"index.svelte":["index.5db1d985.js","client.3b61a7af.js","assets/index-c218c8bc.css","assets/client-431c1c63.css"],"about.svelte":["about.b8847e3b.js","client.3b61a7af.js","assets/client-431c1c63.css"],"blog/index.svelte":["index.1310a7da.js","client.3b61a7af.js","assets/index-a6f64363.css","assets/client-431c1c63.css"],"blog/[slug].svelte":["[slug].27eb9459.js","client.3b61a7af.js","assets/[slug]-870b393e.css","assets/client-431c1c63.css"]},"legacy_assets":{"main":"client.4c0f0167.js"}}